Metadata-Version: 2.4
Name: llama-index-readers-airbyte-cdk
Version: 0.4.1
Summary: llama-index readers airbyte_cdk integration
Author-email: Your Name <you@example.com>
Maintainer: flash1293
License-Expression: GPL-2.0
License-File: LICENSE
Requires-Python: <4.0,>=3.9
Requires-Dist: airbyte-cdk
Requires-Dist: llama-index-core<0.15,>=0.13.0
